mcpdescription/__init__.py
mcpdescription/main.py
description_mcp-0.1.0.dist-info/METADATA
description_mcp-0.1.0.dist-info/WHEEL
description_mcp-0.1.0.dist-info/entry_points.txt
description_mcp-0.1.0.dist-info/RECORD
