Metadata-Version: 2.4
Name: description-mcp
Version: 0.1.0
Summary: Description MCP - declarative & instructive messages to guide LLMs
Author-email: czyhandsome <czyhandsome@foxmail.com>
License: MIT
Keywords: description,llm,mcp,protocol,server
Requires-Python: >=3.12
Requires-Dist: mcp-python>=0.1.4
